factoryos_lib/__init__.py
factoryos_lib/__main__.py
factoryos_lib/base/__init__.py
factoryos_lib/base/_component.py
factoryos_lib/base/_model.py
factoryos_lib/base/_teacher.py
factoryos_lib/base/_trainer.py
factoryos_lib/base/config.py
factoryos_lib/base/mutations.py
factoryos_lib/base/queries.py
factoryos_lib/base/inputs/__init__.py
factoryos_lib/base/inputs/_all_variable.py
factoryos_lib/base/inputs/_input.py
factoryos_lib/base/inputs/_manual.py
factoryos_lib/base/inputs/_variable.py
factoryos_lib/base/inputs/_variables.py
factoryos_lib/base/outputs/__init__.py
factoryos_lib/base/outputs/_output.py
factoryos_lib/base/outputs/_print_output.py
factoryos_lib/base/outputs/_update_datum_output.py
factoryos_lib/execution/__init__.py
factoryos_lib/execution/config.py
factoryos_lib/execution/execute_jobs.py
factoryos_lib/execution/job_list.py
factoryos_lib/execution/utils.py
factoryos_lib/filters/__init__.py
factoryos_lib/filters/_ema.py
factoryos_lib/filters/_filter.py
factoryos_lib/filters/_moving_average.py
factoryos_lib/filters/_stats.py
factoryos_lib/filters/example.py
factoryos_lib/filters/example_ema.py
factoryos_lib/filters/example_ma.py
factoryos_lib/filters/example_stats.py
factoryos_lib/filters/queries.py
factoryos_lib/utils/__init__.py
factoryos_lib/utils/clear.py
factoryos_lib/utils/functions.py
factoryos_lib/utils/plot.py
tests/__init__.py
tests/filters/__init__.py
tests/filters/test_filters.py
factoryos_lib-0.0.13.dist-info/LICENSE
factoryos_lib-0.0.13.dist-info/METADATA
factoryos_lib-0.0.13.dist-info/WHEEL
factoryos_lib-0.0.13.dist-info/top_level.txt
factoryos_lib-0.0.13.dist-info/RECORD
