Metadata-Version: 2.1
Name: factoryos-lib
Version: 0.0.13
Summary: A generic and reusabe package of machine learning models to use for Valiot prodicts
Home-page: https://github.com/valiot/factoryos_lib/
Author: FactoryOS Team
Author-email: FactoryOS Team <factoryos@valiot.io>
Classifier: Programming Language :: Python :: 3
Classifier: Operating System :: OS Independent
Classifier: Intended Audience :: Science/Research
Classifier: Intended Audience :: Developers
Classifier: Topic :: Software Development
Classifier: Topic :: Scientific/Engineering
Requires-Python: >=3.7
License-File: LICENSE
Requires-Dist: deprecated (>=1.2.13)
Requires-Dist: numpy (<1.23,>=1.21.0)
Requires-Dist: pandas (<1.5.0,>=1.1.0)
Requires-Dist: scikit-learn (<1.2.0,>=0.24.0)
Requires-Dist: valiotworker (>=4.0.1)
Requires-Dist: pygqlc (>=3.0.1)
Requires-Dist: tensorflow (>=2.8.1)
Requires-Dist: retrying (>=1.3.3)
Requires-Dist: boto3 (>=1.22.8)
Requires-Dist: protobuf (>=3.20.1)
Requires-Dist: fuzzylab (>=0.13)
Requires-Dist: matplotlib (>=3.6.1)
